rstms_mailgun/__init__.py
rstms_mailgun/cli.py
rstms_mailgun/context.py
rstms_mailgun/exception_handler.py
rstms_mailgun/shell.py
rstms_mailgun/version.py
rstms_mailgun-1.2.6.dist-info/entry_points.txt
rstms_mailgun-1.2.6.dist-info/licenses/LICENSE
rstms_mailgun-1.2.6.dist-info/WHEEL
rstms_mailgun-1.2.6.dist-info/METADATA
rstms_mailgun-1.2.6.dist-info/RECORD
