Metadata-Version: 2.4
Name: rstms-mailgun
Version: 1.2.6
Summary: Top-level package for rstms-mailgun.
Keywords: rstms_mailgun
Author-email: Matt Krueger <mkrueger@rstms.net>
Classifier: Intended Audience :: Developers
Classifier: Natural Language :: English
Classifier: Programming Language :: Python :: 3
Classifier: Programming Language :: Python :: 3.10
License-File: LICENSE
Requires-Dist: click
Requires-Dist: requests
Requires-Dist: rstms-cloudflare
Requires-Dist: black ; extra == "dev"
Requires-Dist: bump2version ; extra == "dev"
Requires-Dist: coverage ; extra == "dev"
Requires-Dist: devtools ; extra == "dev"
Requires-Dist: isort ; extra == "dev"
Requires-Dist: flake8 ; extra == "dev"
Requires-Dist: flake8-length ; extra == "dev"
Requires-Dist: pdbpp ; extra == "dev"
Requires-Dist: pytest ; extra == "dev"
Requires-Dist: python-box ; extra == "dev"
Requires-Dist: toml ; extra == "dev"
Requires-Dist: tox ; extra == "dev"
Requires-Dist: m2r2 ; extra == "docs"
Requires-Dist: sphinx ; extra == "docs"
Requires-Dist: sphinx-click ; extra == "docs"
Requires-Dist: pallets-sphinx-themes ; extra == "docs"
Project-URL: Home, https://github.com/rstms/rstms_mailgun
Provides-Extra: dev
Provides-Extra: docs
